ufonormalizer/__init__.py
ufonormalizer/_version.py
ufonormalizer-0.6.3.dist-info/licenses/LICENSE.txt
ufonormalizer-0.6.3.dist-info/METADATA
ufonormalizer-0.6.3.dist-info/WHEEL
ufonormalizer-0.6.3.dist-info/entry_points.txt
ufonormalizer-0.6.3.dist-info/top_level.txt
ufonormalizer-0.6.3.dist-info/RECORD
