Metadata-Version: 2.4
Name: ufonormalizer
Version: 0.6.3
Summary: Script to normalize the XML and other data inside of a UFO.
Author-email: Tal Leming <tal@typesupply.com>
Project-URL: Homepage, https://github.com/unified-font-object/ufoNormalizer
Classifier: Development Status :: 5 - Production/Stable
Classifier: Environment :: Console
Classifier: Environment :: Other Environment
Classifier: Intended Audience :: Developers
Classifier: Intended Audience :: End Users/Desktop
Classifier: Natural Language :: English
Classifier: Operating System :: OS Independent
Classifier: Programming Language :: Python
Classifier: Programming Language :: Python :: 3
Classifier: Topic :: Multimedia :: Graphics
Classifier: Topic :: Multimedia :: Graphics :: Graphics Conversion
Classifier: Topic :: Text Processing :: Fonts
Requires-Python: >=3.6
License-File: LICENSE.txt
Dynamic: license-file
